shinny_calendar/__init__.py
shinny_calendar/core.py
shinny_calendar-1.0.2026.dist-info/licenses/LICENSE
shinny_calendar-1.0.2026.dist-info/METADATA
shinny_calendar-1.0.2026.dist-info/WHEEL
shinny_calendar-1.0.2026.dist-info/top_level.txt
shinny_calendar-1.0.2026.dist-info/RECORD
