Metadata-Version: 2.4
Name: shinny-calendar
Version: 1.0.2026
Summary: 获取期货交易日的工具，不依赖任何第三方库
Author-email: Yanqiong Ma <mayanqiong@shinnytech.com>
License: MIT License
Project-URL: Homepage, https://github.com/shinnytech/shinny-calendar
Project-URL: Repository, https://github.com/shinnytech/shinny-calendar
Keywords: trading,calendar,finance,futures
Classifier: Development Status :: 3 - Alpha
Classifier: Intended Audience :: Developers
Classifier: License :: OSI Approved :: MIT License
Classifier: Programming Language :: Python :: 3
Requires-Python: >=3.8
License-File: LICENSE
Dynamic: license-file
